mistgen/__init__.py
mistgen/mist.py
mistgen/utils/T_functions.py
mistgen/utils/__init__.py
mistgen/utils/cvxopt_qp.py
mistgen/utils/other_utils.py
test/1_test_qpsolver.py
test/2_test_arrangeT.py
test/3_test_pip.py
test/4_test_yaw.py
test/__init__.py
mistgen-0.2.6.dist-info/LICENSE
mistgen-0.2.6.dist-info/METADATA
mistgen-0.2.6.dist-info/WHEEL
mistgen-0.2.6.dist-info/top_level.txt
mistgen-0.2.6.dist-info/RECORD
